configur/__init__.py
configur/logging_config.py
configur/settings.py
configur-0.1.7.dist-info/LICENSE
configur-0.1.7.dist-info/WHEEL
configur-0.1.7.dist-info/METADATA
configur-0.1.7.dist-info/RECORD
